{
  "streams": [
    {
      "selected": true,
      "tap_stream_id": "submission",
      "key_properties": [],
      "schema": {
        "properties": {
          "id": {
            "type": [
              "integer"
            ]
          },
          "form_id": {
            "type": [
              "integer"
            ]
          },
          "new": {
            "type": [
              "integer"
            ]
          },
          "flag": {
            "type": [
              "integer"
            ]
          },
          "ip": {
            "type": [
              "null",
              "string"
            ]
          },
          "status": {
            "type": [
              "null",
              "string"
            ]
          },
          "created_at": {
            "format": "date-time",
            "type": [
              "null",
              "string"
            ]
          },
          "updated_at": {
            "format": "date-time",
            "type": [
              "null",
              "string"
            ]
          },
          "answers": {
            "type": [
              "object"
            ]
          }
        },
        "type": [
          "object"
        ],
        "additionalProperties": false
      },
      "stream": "submission",
      "metadata": [
        {
          "metadata": {
            "selected": true
          },
          "breadcrumb": []
        }
      ]
    }
  ]
}
